<?xml version="1.0"?>
<font>
  <info face="TinyUnicode" size="12" bold="0" italic="0" charset="" unicode="1" stretchH="100" smooth="0" aa="0" padding="0,0,0,0" spacing="1,1" outline="1"/>
  <common lineHeight="9" base="10" scaleW="256" scaleH="256" pages="1" packed="0" alphaChnl="1" redChnl="0" greenChnl="0" blueChnl="0"/>
  <pages>
    <page id="0" file="tinyunicode_0.png" />
  </pages>
  <chars >
    <char id="32" x="171" y="51" width="5" height="3" xoffset="-2" yoffset="10" xadvance="4" page="0" chnl="15" />
    <char id="33" x="131" y="44" width="3" height="7" xoffset="-1" yoffset="4" xadvance="2" page="0" chnl="15" />
    <char id="34" x="89" y="53" width="5" height="4" xoffset="-1" yoffset="3" xadvance="4" page="0" chnl="15" />
    <!--<char id="35" x="229" y="27" width="7" height="7" xoffset="-1" yoffset="4" xadvance="6" page="0" chnl="15" />-->
    <!--<char id="36" x="36" y="11" width="6" height="8" xoffset="-1" yoffset="4" xadvance="5" page="0" chnl="15" />-->
    <char id="37" x="12" y="46" width="5" height="7" xoffset="-1" yoffset="4" xadvance="4" page="0" chnl="15" />
    <char id="38" x="213" y="28" width="7" height="7" xoffset="-1" yoffset="4" xadvance="6" page="0" chnl="15" />
    <char id="39" x="140" y="52" width="3" height="4" xoffset="-1" yoffset="3" xadvance="2" page="0" chnl="15" />
    <char id="40" x="192" y="0" width="4" height="9" xoffset="-1" yoffset="3" xadvance="3" page="0" chnl="15" />
    <char id="41" x="197" y="0" width="4" height="9" xoffset="-1" yoffset="3" xadvance="3" page="0" chnl="15" />
    <!--<char id="42" x="38" y="54" width="5" height="5" xoffset="-1" yoffset="3" xadvance="4" page="0" chnl="15" />-->
    <char id="42" x="171" y="51" width="5" height="3" xoffset="-2" yoffset="10" xadvance="4" page="0" chnl="15" />
    <char id="43" x="44" y="54" width="5" height="5" xoffset="-1" yoffset="5" xadvance="4" page="0" chnl="15" />
    <char id="44" x="110" y="53" width="4" height="4" xoffset="-1" yoffset="8" xadvance="3" page="0" chnl="15" />
    <char id="45" x="165" y="51" width="5" height="3" xoffset="-1" yoffset="6" xadvance="4" page="0" chnl="15" />
    <char id="46" x="181" y="51" width="3" height="3" xoffset="-1" yoffset="8" xadvance="2" page="0" chnl="15" />
    <char id="47" x="48" y="46" width="5" height="7" xoffset="-1" yoffset="4" xadvance="4" page="0" chnl="15" />
    <char id="48" x="43" y="38" width="6" height="7" xoffset="-1" yoffset="4" xadvance="5" page="0" chnl="15" />
    <char id="49" x="125" y="45" width="6" height="7" xoffset="-1" yoffset="4" xadvance="5" page="0" chnl="15" />
    <char id="50" x="50" y="38" width="6" height="7" xoffset="-1" yoffset="4" xadvance="5" page="0" chnl="15" />
    <char id="51" x="57" y="38" width="6" height="7" xoffset="-1" yoffset="4" xadvance="5" page="0" chnl="15" />
    <char id="52" x="64" y="37" width="6" height="7" xoffset="-1" yoffset="4" xadvance="5" page="0" chnl="15" />
    <char id="53" x="239" y="35" width="6" height="7" xoffset="-1" yoffset="4" xadvance="5" page="0" chnl="15" />
    <char id="54" x="71" y="37" width="6" height="7" xoffset="-1" yoffset="4" xadvance="5" page="0" chnl="15" />
    <char id="55" x="78" y="37" width="6" height="7" xoffset="-1" yoffset="4" xadvance="5" page="0" chnl="15" />
    <char id="56" x="85" y="37" width="6" height="7" xoffset="-1" yoffset="4" xadvance="5" page="0" chnl="15" />
    <char id="57" x="92" y="37" width="6" height="7" xoffset="-1" yoffset="4" xadvance="5" page="0" chnl="15" />
    <char id="58" x="72" y="53" width="3" height="5" xoffset="-1" yoffset="6" xadvance="2" page="0" chnl="15" />
    <char id="59" x="18" y="54" width="4" height="6" xoffset="-1" yoffset="6" xadvance="3" page="0" chnl="15" />
    <char id="60" x="67" y="53" width="4" height="5" xoffset="-1" yoffset="5" xadvance="3" page="0" chnl="15" />
    <char id="61" x="31" y="54" width="6" height="5" xoffset="-1" yoffset="5" xadvance="5" page="0" chnl="15" />
    <!--<char id="62" x="62" y="54" width="4" height="5" xoffset="-1" yoffset="5" xadvance="3" page="0" chnl="15" />-->
    <char id="63" x="8" y="38" width="6" height="7" xoffset="-1" yoffset="4" xadvance="5" page="0" chnl="15" />
    <!--<char id="64" x="90" y="0" width="9" height="9" xoffset="-1" yoffset="3" xadvance="8" page="0" chnl="15" />-->
    <char id="65" x="99" y="37" width="6" height="7" xoffset="-1" yoffset="4" xadvance="5" page="0" chnl="15" />
    <char id="66" x="106" y="37" width="6" height="7" xoffset="-1" yoffset="4" xadvance="5" page="0" chnl="15" />
    <char id="67" x="18" y="46" width="5" height="7" xoffset="-1" yoffset="4" xadvance="4" page="0" chnl="15" />
    <char id="68" x="113" y="37" width="6" height="7" xoffset="-1" yoffset="4" xadvance="5" page="0" chnl="15" />
    <char id="69" x="60" y="46" width="5" height="7" xoffset="-1" yoffset="4" xadvance="4" page="0" chnl="15" />
    <char id="70" x="114" y="45" width="5" height="7" xoffset="-1" yoffset="4" xadvance="4" page="0" chnl="15" />
    <char id="71" x="120" y="37" width="6" height="7" xoffset="-1" yoffset="4" xadvance="5" page="0" chnl="15" />
    <char id="72" x="127" y="36" width="6" height="7" xoffset="-1" yoffset="4" xadvance="5" page="0" chnl="15" />
    <char id="73" x="102" y="45" width="5" height="7" xoffset="-1" yoffset="4" xadvance="4" page="0" chnl="15" />
    <char id="74" x="134" y="36" width="6" height="7" xoffset="-1" yoffset="4" xadvance="5" page="0" chnl="15" />
    <char id="75" x="141" y="36" width="6" height="7" xoffset="-1" yoffset="4" xadvance="5" page="0" chnl="15" />
    <char id="76" x="96" y="45" width="5" height="7" xoffset="-1" yoffset="4" xadvance="4" page="0" chnl="15" />
    <char id="77" x="0" y="38" width="7" height="7" xoffset="-1" yoffset="4" xadvance="6" page="0" chnl="15" />
    <char id="78" x="148" y="36" width="6" height="7" xoffset="-1" yoffset="4" xadvance="5" page="0" chnl="15" />
    <char id="79" x="155" y="36" width="6" height="7" xoffset="-1" yoffset="4" xadvance="5" page="0" chnl="15" />
    <char id="80" x="162" y="36" width="6" height="7" xoffset="-1" yoffset="4" xadvance="5" page="0" chnl="15" />
    <char id="81" x="77" y="19" width="6" height="8" xoffset="-1" yoffset="4" xadvance="5" page="0" chnl="15" />
    <char id="82" x="169" y="36" width="6" height="7" xoffset="-1" yoffset="4" xadvance="5" page="0" chnl="15" />
    <char id="83" x="176" y="36" width="6" height="7" xoffset="-1" yoffset="4" xadvance="5" page="0" chnl="15" />
    <char id="84" x="90" y="45" width="5" height="7" xoffset="-1" yoffset="4" xadvance="4" page="0" chnl="15" />
    <char id="85" x="183" y="36" width="6" height="7" xoffset="-1" yoffset="4" xadvance="5" page="0" chnl="15" />
    <char id="86" x="190" y="36" width="6" height="7" xoffset="-1" yoffset="4" xadvance="5" page="0" chnl="15" />
    <char id="87" x="189" y="28" width="7" height="7" xoffset="-1" yoffset="4" xadvance="6" page="0" chnl="15" />
    <char id="88" x="197" y="36" width="6" height="7" xoffset="-1" yoffset="4" xadvance="5" page="0" chnl="15" />
    <char id="89" x="204" y="36" width="6" height="7" xoffset="-1" yoffset="4" xadvance="5" page="0" chnl="15" />
    <char id="90" x="84" y="45" width="5" height="7" xoffset="-1" yoffset="4" xadvance="4" page="0" chnl="15" />
    <char id="91" x="112" y="28" width="4" height="8" xoffset="-1" yoffset="4" xadvance="3" page="0" chnl="15" />
    <!--<char id="92" x="78" y="45" width="5" height="7" xoffset="-1" yoffset="4" xadvance="4" page="0" chnl="15" />-->
    <char id="93" x="102" y="28" width="4" height="8" xoffset="-1" yoffset="4" xadvance="3" page="0" chnl="15" />
    <!--<char id="94" x="83" y="53" width="5" height="4" xoffset="-1" yoffset="4" xadvance="4" page="0" chnl="15" />-->
    <!--<char id="95" x="144" y="52" width="7" height="3" xoffset="-1" yoffset="9" xadvance="6" page="0" chnl="15" />-->
    <!--<char id="96" x="135" y="52" width="4" height="4" xoffset="-1" yoffset="4" xadvance="3" page="0" chnl="15" />-->
    <char id="97" x="219" y="44" width="6" height="6" xoffset="-1" yoffset="5" xadvance="5" page="0" chnl="15" />
    <char id="98" x="211" y="36" width="6" height="7" xoffset="-1" yoffset="4" xadvance="5" page="0" chnl="15" />
    <char id="99" x="6" y="54" width="5" height="6" xoffset="-1" yoffset="5" xadvance="4" page="0" chnl="15" />
    <char id="100" x="218" y="36" width="6" height="7" xoffset="-1" yoffset="4" xadvance="5" page="0" chnl="15" />
    <char id="101" x="212" y="44" width="6" height="6" xoffset="-1" yoffset="5" xadvance="5" page="0" chnl="15" />
    <char id="102" x="120" y="45" width="5" height="7" xoffset="-1" yoffset="4" xadvance="4" page="0" chnl="15" />
    <char id="103" x="15" y="11" width="6" height="8" xoffset="-1" yoffset="5" xadvance="5" page="0" chnl="15" />
    <char id="104" x="225" y="35" width="6" height="7" xoffset="-1" yoffset="4" xadvance="5" page="0" chnl="15" />
    <char id="105" x="143" y="44" width="3" height="7" xoffset="-1" yoffset="4" xadvance="2" page="0" chnl="15" />
    <char id="106" x="202" y="0" width="4" height="9" xoffset="-1" yoffset="4" xadvance="3" page="0" chnl="15" />
    <char id="107" x="232" y="35" width="6" height="7" xoffset="-1" yoffset="4" xadvance="5" page="0" chnl="15" />
    <char id="108" x="135" y="44" width="3" height="7" xoffset="-1" yoffset="4" xadvance="2" page="0" chnl="15" />
    <char id="109" x="161" y="44" width="7" height="6" xoffset="-1" yoffset="5" xadvance="6" page="0" chnl="15" />
    <char id="110" x="205" y="44" width="6" height="6" xoffset="-1" yoffset="5" xadvance="5" page="0" chnl="15" />
    <char id="111" x="198" y="44" width="6" height="6" xoffset="-1" yoffset="5" xadvance="5" page="0" chnl="15" />
    <char id="112" x="78" y="10" width="6" height="8" xoffset="-1" yoffset="5" xadvance="5" page="0" chnl="15" />
    <char id="113" x="85" y="10" width="6" height="8" xoffset="-1" yoffset="5" xadvance="5" page="0" chnl="15" />
    <char id="114" x="0" y="54" width="5" height="6" xoffset="-1" yoffset="5" xadvance="4" page="0" chnl="15" />
    <char id="115" x="184" y="44" width="6" height="6" xoffset="-1" yoffset="5" xadvance="5" page="0" chnl="15" />
    <char id="116" x="24" y="46" width="5" height="7" xoffset="-1" yoffset="4" xadvance="4" page="0" chnl="15" />
    <char id="117" x="191" y="44" width="6" height="6" xoffset="-1" yoffset="5" xadvance="5" page="0" chnl="15" />
    <char id="118" x="177" y="44" width="6" height="6" xoffset="-1" yoffset="5" xadvance="5" page="0" chnl="15" />
    <char id="119" x="169" y="44" width="7" height="6" xoffset="-1" yoffset="5" xadvance="6" page="0" chnl="15" />
    <char id="120" x="247" y="43" width="5" height="6" xoffset="-1" yoffset="5" xadvance="4" page="0" chnl="15" />
    <char id="121" x="141" y="10" width="6" height="8" xoffset="-1" yoffset="5" xadvance="5" page="0" chnl="15" />
    <char id="122" x="240" y="43" width="6" height="6" xoffset="-1" yoffset="5" xadvance="5" page="0" chnl="15" />
    <!--<char id="123" x="169" y="0" width="5" height="9" xoffset="-1" yoffset="3" xadvance="4" page="0" chnl="15" />-->
    <char id="124" x="147" y="44" width="3" height="7" xoffset="-1" yoffset="4" xadvance="2" page="0" chnl="15" />
    <!--<char id="125" x="175" y="0" width="5" height="9" xoffset="-1" yoffset="3" xadvance="4" page="0" chnl="15" />-->
    <char id="126" x="23" y="54" width="7" height="5" xoffset="-1" yoffset="5" xadvance="6" page="0" chnl="15" />
    <char id="161" x="139" y="44" width="3" height="7" xoffset="-1" yoffset="5" xadvance="2" page="0" chnl="15" />
    <char id="162" x="169" y="10" width="6" height="8" xoffset="-1" yoffset="4" xadvance="5" page="0" chnl="15" />
    <char id="163" x="22" y="38" width="6" height="7" xoffset="-1" yoffset="4" xadvance="5" page="0" chnl="15" />
    <char id="164" x="221" y="27" width="7" height="7" xoffset="-1" yoffset="4" xadvance="6" page="0" chnl="15" />
    <char id="165" x="30" y="46" width="5" height="7" xoffset="-1" yoffset="4" xadvance="4" page="0" chnl="15" />
    <char id="166" x="122" y="28" width="3" height="8" xoffset="-1" yoffset="4" xadvance="2" page="0" chnl="15" />
    <!--<char id="167" x="116" y="0" width="6" height="9" xoffset="-1" yoffset="4" xadvance="5" page="0" chnl="15" />-->
    <char id="168" x="159" y="51" width="5" height="3" xoffset="-1" yoffset="4" xadvance="4" page="0" chnl="15" />
    <char id="169" x="95" y="53" width="4" height="4" xoffset="-1" yoffset="4" xadvance="3" page="0" chnl="15" />
    <char id="170" x="68" y="0" width="10" height="9" xoffset="-1" yoffset="3" xadvance="9" page="0" chnl="15" />
    <char id="171" x="226" y="43" width="6" height="6" xoffset="-1" yoffset="5" xadvance="5" page="0" chnl="15" />
    <char id="172" x="76" y="53" width="6" height="4" xoffset="-1" yoffset="5" xadvance="5" page="0" chnl="15" />
    <!--<char id="174" x="105" y="53" width="4" height="4" xoffset="-1" yoffset="4" xadvance="3" page="0" chnl="15" />
    <char id="175" x="152" y="51" width="6" height="3" xoffset="-1" yoffset="4" xadvance="5" page="0" chnl="15" />-->
    <char id="176" x="56" y="54" width="5" height="5" xoffset="-1" yoffset="4" xadvance="4" page="0" chnl="15" />
    <char id="177" x="66" y="45" width="5" height="7" xoffset="-1" yoffset="4" xadvance="4" page="0" chnl="15" />
    <char id="178" x="130" y="53" width="4" height="4" xoffset="-1" yoffset="4" xadvance="3" page="0" chnl="15" />
    <char id="179" x="115" y="53" width="4" height="4" xoffset="-1" yoffset="4" xadvance="3" page="0" chnl="15" />
    <char id="180" x="120" y="53" width="4" height="4" xoffset="-1" yoffset="4" xadvance="3" page="0" chnl="15" />
    <char id="181" x="176" y="10" width="6" height="8" xoffset="-1" yoffset="5" xadvance="5" page="0" chnl="15" />
    <char id="182" x="237" y="27" width="7" height="7" xoffset="-1" yoffset="4" xadvance="6" page="0" chnl="15" />
    <char id="183" x="177" y="51" width="3" height="3" xoffset="0" yoffset="6" xadvance="3" page="0" chnl="15" />
    <char id="184" x="57" y="0" width="10" height="9" xoffset="-1" yoffset="3" xadvance="9" page="0" chnl="15" />
    <char id="185" x="125" y="53" width="4" height="4" xoffset="-1" yoffset="4" xadvance="3" page="0" chnl="15" />
    <char id="186" x="100" y="53" width="4" height="4" xoffset="-1" yoffset="4" xadvance="3" page="0" chnl="15" />
    <char id="187" x="233" y="43" width="6" height="6" xoffset="-1" yoffset="5" xadvance="5" page="0" chnl="15" />
    <char id="188" x="0" y="0" width="9" height="10" xoffset="-1" yoffset="3" xadvance="8" page="0" chnl="15" />
    <char id="189" x="79" y="0" width="10" height="9" xoffset="-1" yoffset="3" xadvance="9" page="0" chnl="15" />
    <char id="190" x="46" y="0" width="10" height="9" xoffset="-1" yoffset="3" xadvance="9" page="0" chnl="15" />
    <char id="191" x="246" y="35" width="6" height="7" xoffset="-1" yoffset="5" xadvance="5" page="0" chnl="15" />
    <char id="192" x="183" y="10" width="6" height="8" xoffset="-1" yoffset="3" xadvance="5" page="0" chnl="15" />
    <char id="193" x="162" y="10" width="6" height="8" xoffset="-1" yoffset="3" xadvance="5" page="0" chnl="15" />
    <char id="194" x="197" y="10" width="6" height="8" xoffset="-1" yoffset="3" xadvance="5" page="0" chnl="15" />
    <char id="195" x="204" y="10" width="6" height="8" xoffset="-1" yoffset="3" xadvance="5" page="0" chnl="15" />
    <char id="196" x="218" y="9" width="6" height="8" xoffset="-1" yoffset="3" xadvance="5" page="0" chnl="15" />
    <char id="197" x="225" y="9" width="6" height="8" xoffset="-1" yoffset="3" xadvance="5" page="0" chnl="15" />
    <char id="198" x="171" y="28" width="8" height="7" xoffset="-1" yoffset="4" xadvance="7" page="0" chnl="15" />
    <char id="199" x="163" y="0" width="5" height="9" xoffset="-1" yoffset="4" xadvance="4" page="0" chnl="15" />
    <char id="200" x="236" y="18" width="5" height="8" xoffset="-1" yoffset="3" xadvance="4" page="0" chnl="15" />
    <char id="201" x="0" y="29" width="5" height="8" xoffset="-1" yoffset="3" xadvance="4" page="0" chnl="15" />
    <char id="202" x="72" y="45" width="5" height="7" xoffset="-1" yoffset="4" xadvance="4" page="0" chnl="15" />
    <char id="203" x="30" y="29" width="5" height="8" xoffset="-1" yoffset="3" xadvance="4" page="0" chnl="15" />
    <char id="204" x="78" y="28" width="5" height="8" xoffset="-1" yoffset="3" xadvance="4" page="0" chnl="15" />
    <char id="205" x="36" y="29" width="5" height="8" xoffset="-1" yoffset="3" xadvance="4" page="0" chnl="15" />
    <char id="206" x="42" y="29" width="5" height="8" xoffset="-1" yoffset="3" xadvance="4" page="0" chnl="15" />
    <char id="207" x="66" y="28" width="5" height="8" xoffset="-1" yoffset="3" xadvance="4" page="0" chnl="15" />
    <char id="208" x="126" y="28" width="11" height="7" xoffset="-1" yoffset="5" xadvance="10" page="0" chnl="15" />
    <char id="209" x="232" y="9" width="6" height="8" xoffset="-1" yoffset="3" xadvance="5" page="0" chnl="15" />
    <char id="210" x="239" y="9" width="6" height="8" xoffset="-1" yoffset="3" xadvance="5" page="0" chnl="15" />
    <char id="211" x="246" y="9" width="6" height="8" xoffset="-1" yoffset="3" xadvance="5" page="0" chnl="15" />
    <char id="212" x="0" y="20" width="6" height="8" xoffset="-1" yoffset="3" xadvance="5" page="0" chnl="15" />
    <char id="213" x="7" y="20" width="6" height="8" xoffset="-1" yoffset="3" xadvance="5" page="0" chnl="15" />
    <char id="214" x="14" y="20" width="6" height="8" xoffset="-1" yoffset="3" xadvance="5" page="0" chnl="15" />
    <char id="215" x="50" y="54" width="5" height="5" xoffset="-1" yoffset="5" xadvance="4" page="0" chnl="15" />
    <char id="216" x="108" y="0" width="7" height="9" xoffset="-1" yoffset="3" xadvance="6" page="0" chnl="15" />
    <char id="217" x="21" y="20" width="6" height="8" xoffset="-1" yoffset="3" xadvance="5" page="0" chnl="15" />
    <char id="218" x="28" y="20" width="6" height="8" xoffset="-1" yoffset="3" xadvance="5" page="0" chnl="15" />
    <char id="219" x="35" y="20" width="6" height="8" xoffset="-1" yoffset="3" xadvance="5" page="0" chnl="15" />
    <char id="220" x="42" y="20" width="6" height="8" xoffset="-1" yoffset="3" xadvance="5" page="0" chnl="15" />
    <char id="221" x="49" y="20" width="6" height="8" xoffset="-1" yoffset="3" xadvance="5" page="0" chnl="15" />
    <char id="222" x="36" y="46" width="5" height="7" xoffset="-1" yoffset="4" xadvance="4" page="0" chnl="15" />
    <char id="223" x="54" y="29" width="5" height="8" xoffset="-1" yoffset="4" xadvance="4" page="0" chnl="15" />
    <char id="224" x="211" y="9" width="6" height="8" xoffset="-1" yoffset="3" xadvance="5" page="0" chnl="15" />
    <char id="225" x="56" y="19" width="6" height="8" xoffset="-1" yoffset="3" xadvance="5" page="0" chnl="15" />
    <char id="226" x="63" y="19" width="6" height="8" xoffset="-1" yoffset="3" xadvance="5" page="0" chnl="15" />
    <char id="227" x="70" y="19" width="6" height="8" xoffset="-1" yoffset="3" xadvance="5" page="0" chnl="15" />
    <char id="228" x="84" y="19" width="6" height="8" xoffset="-1" yoffset="3" xadvance="5" page="0" chnl="15" />
    <char id="229" x="91" y="19" width="6" height="8" xoffset="-1" yoffset="3" xadvance="5" page="0" chnl="15" />
    <char id="230" x="151" y="44" width="9" height="6" xoffset="-1" yoffset="5" xadvance="8" page="0" chnl="15" />
    <char id="231" x="84" y="28" width="5" height="8" xoffset="-1" yoffset="5" xadvance="4" page="0" chnl="15" />
    <char id="232" x="98" y="19" width="6" height="8" xoffset="-1" yoffset="3" xadvance="5" page="0" chnl="15" />
    <char id="233" x="105" y="19" width="6" height="8" xoffset="-1" yoffset="3" xadvance="5" page="0" chnl="15" />
    <char id="234" x="112" y="19" width="6" height="8" xoffset="-1" yoffset="3" xadvance="5" page="0" chnl="15" />
    <char id="235" x="119" y="19" width="6" height="8" xoffset="-1" yoffset="3" xadvance="5" page="0" chnl="15" />
    <char id="236" x="107" y="28" width="4" height="8" xoffset="-1" yoffset="3" xadvance="3" page="0" chnl="15" />
    <char id="237" x="117" y="28" width="4" height="8" xoffset="-1" yoffset="3" xadvance="3" page="0" chnl="15" />
    <char id="238" x="18" y="29" width="5" height="8" xoffset="-1" yoffset="3" xadvance="4" page="0" chnl="15" />
    <char id="239" x="6" y="46" width="5" height="7" xoffset="-1" yoffset="4" xadvance="4" page="0" chnl="15" />
    <char id="240" x="245" y="0" width="7" height="8" xoffset="-1" yoffset="3" xadvance="6" page="0" chnl="15" />
    <char id="241" x="126" y="19" width="6" height="8" xoffset="-1" yoffset="3" xadvance="5" page="0" chnl="15" />
    <char id="242" x="133" y="19" width="6" height="8" xoffset="-1" yoffset="3" xadvance="5" page="0" chnl="15" />
    <char id="243" x="140" y="19" width="6" height="8" xoffset="-1" yoffset="3" xadvance="5" page="0" chnl="15" />
    <char id="244" x="147" y="19" width="6" height="8" xoffset="-1" yoffset="3" xadvance="5" page="0" chnl="15" />
    <!--<char id="245" x="154" y="19" width="6" height="8" xoffset="-1" yoffset="3" xadvance="5" page="0" chnl="15" />-->
    <char id="246" x="161" y="19" width="6" height="8" xoffset="-1" yoffset="3" xadvance="5" page="0" chnl="15" />
    <char id="247" x="197" y="28" width="7" height="7" xoffset="-1" yoffset="4" xadvance="6" page="0" chnl="15" />
    <char id="248" x="168" y="19" width="6" height="8" xoffset="-1" yoffset="4" xadvance="5" page="0" chnl="15" />
    <char id="249" x="175" y="19" width="6" height="8" xoffset="-1" yoffset="3" xadvance="5" page="0" chnl="15" />
    <char id="250" x="182" y="19" width="6" height="8" xoffset="-1" yoffset="3" xadvance="5" page="0" chnl="15" />
    <char id="251" x="189" y="19" width="6" height="8" xoffset="-1" yoffset="3" xadvance="5" page="0" chnl="15" />
    <char id="252" x="196" y="19" width="6" height="8" xoffset="-1" yoffset="3" xadvance="5" page="0" chnl="15" />
    <char id="253" x="144" y="0" width="6" height="9" xoffset="-1" yoffset="4" xadvance="5" page="0" chnl="15" />
    <char id="254" x="207" y="0" width="11" height="8" xoffset="-1" yoffset="4" xadvance="10" page="0" chnl="15" />
    <char id="255" x="137" y="0" width="6" height="9" xoffset="-1" yoffset="4" xadvance="5" page="0" chnl="15" />
    <char id="256" x="190" y="10" width="6" height="8" xoffset="-1" yoffset="3" xadvance="5" page="0" chnl="15" />
    <char id="257" x="203" y="19" width="6" height="8" xoffset="-1" yoffset="3" xadvance="5" page="0" chnl="15" />
    <char id="258" x="210" y="19" width="6" height="8" xoffset="-1" yoffset="3" xadvance="5" page="0" chnl="15" />
    <char id="259" x="217" y="18" width="6" height="8" xoffset="-1" yoffset="3" xadvance="5" page="0" chnl="15" />
    <char id="260" x="130" y="0" width="6" height="9" xoffset="-1" yoffset="4" xadvance="5" page="0" chnl="15" />
    <char id="261" x="8" y="11" width="6" height="8" xoffset="-1" yoffset="5" xadvance="5" page="0" chnl="15" />
    <char id="262" x="72" y="28" width="5" height="8" xoffset="-1" yoffset="3" xadvance="4" page="0" chnl="15" />
    <char id="263" x="60" y="28" width="5" height="8" xoffset="-1" yoffset="3" xadvance="4" page="0" chnl="15" />
    <char id="264" x="248" y="18" width="5" height="8" xoffset="-1" yoffset="3" xadvance="4" page="0" chnl="15" />
    <char id="265" x="230" y="18" width="5" height="8" xoffset="-1" yoffset="3" xadvance="4" page="0" chnl="15" />
    <char id="266" x="224" y="18" width="5" height="8" xoffset="-1" yoffset="3" xadvance="4" page="0" chnl="15" />
    <char id="267" x="90" y="28" width="5" height="8" xoffset="-1" yoffset="3" xadvance="4" page="0" chnl="15" />
    <char id="268" x="242" y="18" width="5" height="8" xoffset="-1" yoffset="3" xadvance="4" page="0" chnl="15" />
    <char id="269" x="12" y="29" width="5" height="8" xoffset="-1" yoffset="3" xadvance="4" page="0" chnl="15" />
    <char id="270" x="22" y="11" width="6" height="8" xoffset="-1" yoffset="3" xadvance="5" page="0" chnl="15" />
    <char id="271" x="219" y="0" width="8" height="8" xoffset="-1" yoffset="3" xadvance="7" page="0" chnl="15" />
    <char id="272" x="205" y="28" width="7" height="7" xoffset="-1" yoffset="4" xadvance="6" page="0" chnl="15" />
    <char id="273" x="29" y="11" width="6" height="8" xoffset="-1" yoffset="3" xadvance="5" page="0" chnl="15" />
    <char id="274" x="181" y="0" width="5" height="9" xoffset="-1" yoffset="2" xadvance="4" page="0" chnl="15" />
    <char id="275" x="43" y="11" width="6" height="8" xoffset="-1" yoffset="3" xadvance="5" page="0" chnl="15" />
    <char id="276" x="6" y="29" width="5" height="8" xoffset="-1" yoffset="3" xadvance="4" page="0" chnl="15" />
    <char id="277" x="50" y="10" width="6" height="8" xoffset="-1" yoffset="3" xadvance="5" page="0" chnl="15" />
    <char id="278" x="96" y="28" width="5" height="8" xoffset="-1" yoffset="3" xadvance="4" page="0" chnl="15" />
    <char id="279" x="57" y="10" width="6" height="8" xoffset="-1" yoffset="3" xadvance="5" page="0" chnl="15" />
    <char id="280" x="157" y="0" width="5" height="9" xoffset="-1" yoffset="4" xadvance="4" page="0" chnl="15" />
    <char id="281" x="64" y="10" width="6" height="8" xoffset="-1" yoffset="5" xadvance="5" page="0" chnl="15" />
    <char id="282" x="24" y="29" width="5" height="8" xoffset="-1" yoffset="3" xadvance="4" page="0" chnl="15" />
    <char id="283" x="71" y="10" width="6" height="8" xoffset="-1" yoffset="3" xadvance="5" page="0" chnl="15" />
    <char id="284" x="92" y="10" width="6" height="8" xoffset="-1" yoffset="3" xadvance="5" page="0" chnl="15" />
    <char id="285" x="26" y="0" width="6" height="10" xoffset="-1" yoffset="3" xadvance="5" page="0" chnl="15" />
    <char id="286" x="99" y="10" width="6" height="8" xoffset="-1" yoffset="3" xadvance="5" page="0" chnl="15" />
    <char id="287" x="33" y="0" width="6" height="10" xoffset="-1" yoffset="3" xadvance="5" page="0" chnl="15" />
    <char id="294" x="228" y="0" width="8" height="8" xoffset="-1" yoffset="3" xadvance="7" page="0" chnl="15" />
    <char id="312" x="12" y="54" width="5" height="6" xoffset="-1" yoffset="5" xadvance="4" page="0" chnl="15" />
    <char id="321" x="15" y="38" width="6" height="7" xoffset="-1" yoffset="4" xadvance="5" page="0" chnl="15" />
    <char id="322" x="54" y="46" width="5" height="7" xoffset="-1" yoffset="4" xadvance="4" page="0" chnl="15" />
    <char id="328" x="106" y="10" width="6" height="8" xoffset="-1" yoffset="3" xadvance="5" page="0" chnl="15" />
    <char id="331" x="113" y="10" width="6" height="8" xoffset="-1" yoffset="5" xadvance="5" page="0" chnl="15" />
    <char id="338" x="180" y="28" width="8" height="7" xoffset="-1" yoffset="4" xadvance="7" page="0" chnl="15" />
    <char id="342" x="0" y="11" width="7" height="8" xoffset="-1" yoffset="3" xadvance="6" page="0" chnl="15" />
    <char id="343" x="48" y="29" width="5" height="8" xoffset="-1" yoffset="5" xadvance="4" page="0" chnl="15" />
    <char id="354" x="151" y="0" width="5" height="9" xoffset="-1" yoffset="4" xadvance="4" page="0" chnl="15" />
    <char id="355" x="187" y="0" width="4" height="9" xoffset="-1" yoffset="4" xadvance="3" page="0" chnl="15" />
    <char id="358" x="245" y="27" width="7" height="7" xoffset="-1" yoffset="4" xadvance="6" page="0" chnl="15" />
    <char id="367" x="120" y="10" width="6" height="8" xoffset="-1" yoffset="3" xadvance="5" page="0" chnl="15" />
    <char id="370" x="127" y="10" width="6" height="8" xoffset="-1" yoffset="4" xadvance="5" page="0" chnl="15" />
    <char id="371" x="134" y="10" width="6" height="8" xoffset="-1" yoffset="5" xadvance="5" page="0" chnl="15" />
    <char id="376" x="123" y="0" width="6" height="9" xoffset="-1" yoffset="4" xadvance="5" page="0" chnl="15" />
    <char id="377" x="42" y="46" width="5" height="7" xoffset="-1" yoffset="4" xadvance="4" page="0" chnl="15" />
    <char id="378" x="148" y="10" width="6" height="8" xoffset="-1" yoffset="3" xadvance="5" page="0" chnl="15" />
    <char id="8592" x="138" y="28" width="10" height="7" xoffset="-1" yoffset="4" xadvance="9" page="0" chnl="15" />
    <char id="8593" x="100" y="0" width="7" height="9" xoffset="-1" yoffset="3" xadvance="6" page="0" chnl="15" />
    <char id="8594" x="149" y="28" width="10" height="7" xoffset="-1" yoffset="4" xadvance="9" page="0" chnl="15" />
    <char id="8595" x="18" y="0" width="7" height="10" xoffset="-1" yoffset="3" xadvance="6" page="0" chnl="15" />
    <char id="8596" x="160" y="28" width="10" height="7" xoffset="-1" yoffset="4" xadvance="9" page="0" chnl="15" />
    <char id="8597" x="10" y="0" width="7" height="10" xoffset="-1" yoffset="3" xadvance="6" page="0" chnl="15" />
    <char id="8721" x="155" y="10" width="6" height="8" xoffset="-1" yoffset="4" xadvance="5" page="0" chnl="15" />
    <char id="8730" x="237" y="0" width="7" height="8" xoffset="-1" yoffset="3" xadvance="6" page="0" chnl="15" />
    <char id="8747" x="40" y="0" width="5" height="10" xoffset="-1" yoffset="3" xadvance="4" page="0" chnl="15" />
    <char id="8776" x="29" y="38" width="6" height="7" xoffset="-1" yoffset="4" xadvance="5" page="0" chnl="15" />
    <char id="8800" x="36" y="38" width="6" height="7" xoffset="-1" yoffset="4" xadvance="5" page="0" chnl="15" />
    <char id="8804" x="108" y="45" width="5" height="7" xoffset="-1" yoffset="4" xadvance="4" page="0" chnl="15" />
    <char id="8805" x="0" y="46" width="5" height="7" xoffset="-1" yoffset="4" xadvance="4" page="0" chnl="15" />


     <char id="347" x="13" y="60" width="6" height="8" xoffset="-1" yoffset="3" xadvance="5" page="0" chnl="15" />
     <char id="380" x="0" y="60" width="6" height="8" xoffset="-1" yoffset="3" xadvance="5" page="0" chnl="15" />
     <char id="324" x="27" y="60" width="6" height="8" xoffset="-1" yoffset="3" xadvance="5" page="0" chnl="15" />
     <char id="379" x="7" y="60" width="6" height="8" xoffset="-1" yoffset="3" xadvance="5" page="0" chnl="15" />
     <char id="346" x="20" y="60" width="6" height="8" xoffset="-1" yoffset="3" xadvance="5" page="0" chnl="15" />
     <char id="323" x="34" y="60" width="6" height="8" xoffset="-1" yoffset="3" xadvance="5" page="0" chnl="15" />

     <char id="64" x="0" y="69" width="10" height="10" xoffset="0" yoffset="3" xadvance="11" page="0" chnl="15" />
     <char id="35" x="12" y="69" width="11" height="10" xoffset="0" yoffset="2" xadvance="12" page="0" chnl="15" />
     <char id="36" x="26" y="69" width="8" height="10" xoffset="0" yoffset="2" xadvance="4" page="0" chnl="15" />
     <char id="94" x="0" y="80" width="7" height="10" xoffset="0" yoffset="2" xadvance="8" page="0" chnl="15" />
     <char id="96" x="37" y="69" width="8" height="10" xoffset="0" yoffset="2" xadvance="4" page="0" chnl="15" />



     <!-- x -->

      <char id="123" x="48" y="69" width="10" height="10" xoffset="0" yoffset="3" xadvance="11" page="0" chnl="15" />
      <char id="125" x="171" y="51" width="2" height="3" xoffset="-2" yoffset="10" xadvance="2" page="0" chnl="15" /> 

      <char id="126" x="0" y="91" width="10" height="10" xoffset="0" yoffset="2" xadvance="10" page="0" chnl="15" />
      <char id="95" x="11" y="91" width="10" height="10" xoffset="0" yoffset="2" xadvance="10" page="0" chnl="15" />
      <char id="92" x="22" y="91" width="10" height="10" xoffset="0" yoffset="2" xadvance="10" page="0" chnl="15" />
      
      <char id="62" x="149" y="28" width="10" height="7" xoffset="0" yoffset="4" xadvance="10" page="0" chnl="15" />

  </chars>
</font>
